.gitignore
LICENSE
README.rst
requirements.txt
setup.py
tox.ini
docs/CHANGELOG.rst
docs/Makefile
docs/README.rst
docs/conf.py
docs/index.rst
docs/api/objects.rst
memory_tools.egg-info/PKG-INFO
memory_tools.egg-info/SOURCES.txt
memory_tools.egg-info/dependency_links.txt
memory_tools.egg-info/entry_points.txt
memory_tools.egg-info/requires.txt
memory_tools.egg-info/top_level.txt
memorytools/__init__.py
memorytools/loop.py
memorytools/show_mem.py
test/conftest.py
test/test_loop.py
test/test_objects.py
test/test_show_mem.py
test/utils.py