Metadata-Version: 1.1
Name: memory-tools
Version: 1.0.5
Summary: A set of simple yet effective tools to troubleshoot memory leaks.
Home-page: https://github.com/maxzheng/memory-tools
Author: Max Zheng
Author-email: maxzheng.os @t gmail.com
License: MIT
Keywords: memory tools leaks profiler simple easy to use process usage private rss total
Platform: UNKNOWN
Classifier: Development Status :: 5 - Production/Stable
Classifier: Intended Audience :: Developers
Classifier: Topic :: Software Development
Classifier: License :: OSI Approved :: MIT License
Classifier: Programming Language :: Python :: 2
Classifier: Programming Language :: Python :: 2.6
Classifier: Programming Language :: Python :: 2.7
